{
    "IsActive": true,
    "IsOmniScriptEmbeddable": false,
    "Name": "ESMGetCartsPromotionsResponseAction",
    "OmniProcessId": {
        "Name": "ESMGetCartsProducts",
        "VlocityDataPackType": "VlocityMatchingKeyObject",
        "VlocityMatchingRecordSourceKey": "OmniProcess/ESM/GetCartsProducts/Procedure",
        "VlocityRecordSObjectType": "OmniProcess"
    },
    "ParentElementId": {
        "Name": "OnlyPromotions",
        "OmniProcessId": {
            "Name": "ESMGetCartsProducts",
            "VlocityDataPackType": "VlocityMatchingKeyObject",
            "VlocityMatchingRecordSourceKey": "OmniProcess/ESM/GetCartsProducts/Procedure",
            "VlocityRecordSObjectType": "OmniProcess"
        },
        "VlocityDataPackType": "VlocityMatchingKeyObject",
        "VlocityMatchingRecordSourceKey": "OmniProcessElement/OmniProcess/ESM/GetCartsProducts/Procedure/OnlyPromotions",
        "VlocityRecordSObjectType": "OmniProcessElement"
    },
    "ParentElementName": "OnlyPromotions",
    "ParentElementType": "Conditional Block",
    "PropertySetConfig": {
        "additionalOutput": {
            "data": "%ESMGetCartsPromotionListAction%",
            "productsSize": "%getCartsProducts:totalSize%",
            "promotionsSize": "%getCartsPromotions:totalSize%"
        },
        "disOnTplt": false,
        "executionConditionalFormula": "",
        "label": "ResponseAction1",
        "responseDefaultData": {
        },
        "responseFormat": "JSON",
        "responseJSONNode": "",
        "responseJSONPath": "",
        "returnFullDataJSON": false,
        "returnOnlyAdditionalOutput": false,
        "sendJSONNode": "",
        "sendJSONPath": "",
        "show": null,
        "useFormulas": true,
        "vlcResponseHeaders": {
        }
    },
    "Type": "Response Action",
    "VlocityDataPackType": "SObject",
    "VlocityRecordSObjectType": "OmniProcessElement",
    "VlocityRecordSourceKey": "OmniProcessElement/OmniProcess/ESM/GetCartsProducts/Procedure/ESMGetCartsPromotionsResponseAction"
}