{
    "IsActive": true,
    "IsOmniScriptEmbeddable": false,
    "Name": "ProductSpecificationFailureResponse",
    "OmniProcessId": {
        "Name": "TMFTMForumPatchProductSpecification",
        "VlocityDataPackType": "VlocityMatchingKeyObject",
        "VlocityMatchingRecordSourceKey": "OmniProcess/tmf/TMForumPatchProductSpecification/Procedure",
        "VlocityRecordSObjectType": "OmniProcess"
    },
    "PropertySetConfig": {
        "additionalOutput": {
        },
        "disOnTplt": false,
        "executionConditionalFormula": "%PatchProductSpecificationRequestRA:epcResponse:overallResult% == 'failure'",
        "label": "ResponseAction2",
        "responseDefaultData": {
        },
        "responseFormat": "JSON",
        "responseJSONNode": "",
        "responseJSONPath": "",
        "returnFullDataJSON": false,
        "returnOnlyAdditionalOutput": false,
        "sendJSONNode": "",
        "sendJSONPath": "",
        "show": null,
        "useFormulas": true,
        "vlcResponseHeaders": {
        }
    },
    "Type": "Response Action",
    "VlocityDataPackType": "SObject",
    "VlocityRecordSObjectType": "OmniProcessElement",
    "VlocityRecordSourceKey": "OmniProcessElement/OmniProcess/tmf/TMForumPatchProductSpecification/Procedure/ProductSpecificationFailureResponse"
}